pretix_banktool/__init__.py
pretix_banktool/config.py
pretix_banktool/main.py
pretix_banktool/testing.py
pretix_banktool/upload.py
pretix_banktool/utils.py
pretix_banktool-1.1.0.dist-info/LICENSE
pretix_banktool-1.1.0.dist-info/METADATA
pretix_banktool-1.1.0.dist-info/WHEEL
pretix_banktool-1.1.0.dist-info/entry_points.txt
pretix_banktool-1.1.0.dist-info/top_level.txt
pretix_banktool-1.1.0.dist-info/RECORD
