Metadata-Version: 2.1
Name: pretix-banktool
Version: 1.1.0
Summary: Command-line client for pretix that allows to synchronize bank transaction statements to pretix
Author-email: pretix team <support@pretix.eu>
License: GPL-3.0-Only
Keywords: pretix,fints,bank
Classifier: License :: OSI Approved :: GNU General Public License v3 (GPLv3)
Classifier: Programming Language :: Python :: 3
Requires-Python: >=3.9
License-File: LICENSE
Requires-Dist: click <9,>=6
Requires-Dist: fints ==4.*,>=4.2.0
Requires-Dist: requests
Requires-Dist: mt-940 >=4.12
